{
    "AS_UWI_afa3127b8aea4123ba3949206f155202": {
        "id": "AS_UWI_afa3127b8aea4123ba3949206f155202",
        "type": "ACTION_SEQUENCE",
        "params": [{
            "datatype": "collection",
            "name": "eventobject"
        }],
        "language": "js",
        "eventType": "onClick",
        "actions": [{
            "id": "_ide_onClick_f5a89b1ec5444d28bf65611be695e972",
            "type": "MOVE_ACTION",
            "itemType": "FORM",
            "itemId": "frmClaimList",
            "widgetId": "LeftMenu",
            "itemKUID": "ba850a2fb9534149873fbb6f82119a8d",
            "widgetKUID": "b16e9c9f8d81487d9dce0dc9ad6e7699",
            "wType": "UserWidgetInstance",
            "animationObject": {
                "left": "-100%",
                "anchorPoint": {},
                "stepConfig": {
                    "timingFunction": "kony.anim.EASE"
                }
            },
            "config": {
                "delay": "0",
                "iterationCount": 1,
                "fillMode": "kony.anim.FILL_MODE_FORWARDS",
                "duration": "250"
            },
            "start": "Immediately",
            "animationId": "MOVE_ACTION_i30f9d2d49d64e6eb1dc2fe21c614014",
            "displayAnimationId": "MOVE_ACTION_i30f9d2d49d64e6eb1dc2fe21c614014",
            "forkedPlatform": "all",
            "widgetPath": "this.view.LeftMenu"
        }, {
            "id": "NAVIGATE_TO_FORM__ide_onClick_f45721b7563a44ee85e595d73e0ed81b",
            "type": "NAVIGATE_TO_FORM",
            "formId": "frmClaimNew",
            "formKUID": "i485d7da04114659b706a6407a9bed34",
            "projectName": "OpusOneDemo",
            "mappings": {},
            "mappingsOrder": [],
            "parentId": "_ide_onClick_f5a89b1ec5444d28bf65611be695e972",
            "callbackType": "Callback",
            "enableMappingEditor": true,
            "package": "",
            "isCustomInput": false
        }]
    }
}